{
  "collectionName": "components_home_lookup_home_lookups",
  "info": {
    "displayName": "Lookup",
    "description": ""
  },
  "options": {},
  "attributes": {
    "title": {
      "type": "string",
      "required": true
    },
    "background": {
      "type": "media",
      "multiple": false,
      "required": true,
      "allowedTypes": [
        "images"
      ]
    },
    "contacts": {
      "type": "component",
      "repeatable": true,
      "component": "home.service-contact",
      "required": true
    }
  }
}
